{
  "default": {
    "save"      : {"key": "S", "ctrlKey": true},
    "copy"      : {"key": "C", "ctrlKey": true},
    "paste"     : {"key": "V", "ctrlKey": true},
    "cut"       : {"key": "X", "ctrlKey": true},
    "undo"      : {"key": "Z", "ctrlKey": true},
    "redo"      : [
      {"key": "Y", "ctrlKey": true},
      {"key": "Z", "ctrlKey": true, "shiftKey": true}
    ],
    "delete"    : [
      {"code": "Backspace"},
      {"code": "Delete"}
    ],
    "cancel"    : {"code": "Escape"}
  },

  "environment": {
    "new"       : {"key": "N" },
    "open"      : {"key": "O", "ctrlKey": true}
  },

  "editor": {
    "connect"   : {"key": "C"},

    "move-left" : {"code": "ArrowLeft", "ctrlKey":true},
    "move-up"   : {"code": "ArrowUp", "ctrlKey":true},
    "move-right": {"code": "ArrowRight", "ctrlKey":true},
    "move-down" : {"code": "ArrowDown", "ctrlKey":true},
    "move-frontward": { "code": "PageUp" },
    "move-backward" : { "code": "PageDown" },
    "move-front": {"code": "PageUp", "shiftKey": true},
    "move-back" : {"code": "PageDown", "shiftKey": true},

    "zoom-in"   : {"key": "+"},
    "zoom-out"  : {"key": "-"},
    "view-left" : {"code": "ArrowLeft"},
    "view-up"   : {"code": "ArrowUp"},
    "view-right": {"code": "ArrowRight"},
    "view-down" : {"code": "ArrowDown"},
    "view-full" : {"key": "F"}
  }
}